README.txt
setup.py
cbio/__init__.py
cbio/__main__.py
cbio/cbio.py
cbio/main_process.py
cbio/messages.py
cbio/processes.py
cbio.egg-info/PKG-INFO
cbio.egg-info/SOURCES.txt
cbio.egg-info/dependency_links.txt
cbio.egg-info/entry_points.txt
cbio.egg-info/not-zip-safe
cbio.egg-info/requires.txt
cbio.egg-info/top_level.txt
cbio/biofiles/__init__.py
cbio/biofiles/bed.py
cbio/biofiles/vcf.py
cbio/dbs/__init__.py
cbio/dbs/ensembl_db.py
cbio/dbs/ucsc_db.py
cbio/dbs/tests/__init__.py
cbio/dbs/tests/test_001.py
cbio/pipeline/__init__.py
cbio/tools/__init__.py
cbio/tools/biodata.py
cbio/tools/database.py
cbio/tools/system_func.py
cbio/tools/utils.py
cbio/tools/utils/__init__.py
cbio/tools/utils/configuration.py
cbio/utils/__init__.py
cbio/utils/utils.py